__init__.py
websitecategorization/__init__.py
websitecategorization/client.py
websitecategorization/version.py
websitecategorization/exceptions/__init__.py
websitecategorization/exceptions/error.py
websitecategorization/models/__init__.py
websitecategorization/models/base.py
websitecategorization/models/response.py
websitecategorization/net/__init__.py
websitecategorization/net/http.py
website_categorization-1.1.2.dist-info/AUTHORS.rst
website_categorization-1.1.2.dist-info/LICENSE
website_categorization-1.1.2.dist-info/METADATA
website_categorization-1.1.2.dist-info/WHEEL
website_categorization-1.1.2.dist-info/top_level.txt
website_categorization-1.1.2.dist-info/RECORD
